hubmodule/__init__.py
hubmodule/_rls_generator.py
hubmodule/_setup.py
hubmodule/models.py
hubmodule/migrations/0001_initial.py
hubmodule/migrations/__init__.py
hubmodule/sql/1-setup-extensions.sql
hubmodule/sql/2-setup-secret.sql
hubmodule/sql/3-setup-utils-jwt.sql
hubmodule-0.1.0.dist-info/WHEEL
hubmodule-0.1.0.dist-info/METADATA
hubmodule-0.1.0.dist-info/RECORD
